smallml/__init__.py
smallml/feature_matcher.py
smallml/pipeline.py
smallml/version.py
smallml/data/priors_churn.pkl
smallml/layer2/__init__.py
smallml/layer2/hierarchical_model.py
smallml/layer2/sme_data_generator.py
smallml/layer3/__init__.py
smallml/layer3/conformal_predictor.py
smallml/layer3/prediction_sets.py
smallml-0.1.4.dist-info/licenses/LICENSE
smallml-0.1.4.dist-info/METADATA
smallml-0.1.4.dist-info/WHEEL
smallml-0.1.4.dist-info/top_level.txt
smallml-0.1.4.dist-info/RECORD
