Metadata-Version: 2.4
Name: smallml
Version: 0.1.4
Summary: Bayesian Transfer Learning for Small-Data Predictive Analytics
Home-page: https://github.com/seemyon/smallml
Author: Semen Leontev
Author-email: Semen Leontev <leontyev.s@gmail.com>
License: MIT
Project-URL: Homepage, https://github.com/seemyon/smallml
Project-URL: Bug Tracker, https://github.com/seemyon/smallml/issues
Keywords: machine-learning,bayesian,transfer-learning,small-data
Classifier: Programming Language :: Python :: 3
Classifier: License :: OSI Approved :: MIT License
Classifier: Operating System :: OS Independent
Requires-Python: >=3.9
License-File: LICENSE
Requires-Dist: pymc>=5.0.0
Requires-Dist: arviz>=0.18.0
Requires-Dist: numpy<2.2.0,>=1.24.0
Requires-Dist: pandas>=2.0.0
Requires-Dist: scikit-learn>=1.3.0
Requires-Dist: scipy>=1.10.0
Dynamic: author
Dynamic: home-page
Dynamic: license-file
Dynamic: requires-python
